payeezy/__generate_hmac.py
payeezy/__init__.py
payeezy/__make_headers.py
payeezy/__make_request_bodies.py
payeezy/api.py
payeezy/transactions.py
tests/__init__.py
tests/test_api.py
tests/test_generate_hmac.py
tests/test_make_headers.py
tests/test_make_request_bodies.py
payeezy-1.1.2.dist-info/LICENSE.md
payeezy-1.1.2.dist-info/METADATA
payeezy-1.1.2.dist-info/WHEEL
payeezy-1.1.2.dist-info/top_level.txt
payeezy-1.1.2.dist-info/RECORD
