Metadata-Version: 2.1
Name: payeezy
Version: 1.1.2
Summary: Unofficial Python 3 module to process basic(purchase and authorize) transactions with Payeezy
Home-page: https://github.com/lemmetry/payeezy
Author: Artem Kisel
Author-email: artem.a.kisel@gmail.com
License: UNKNOWN
Keywords: Payeezy purchase authorize transaction FirstData
Platform: UNKNOWN
Classifier: Development Status :: 3 - Alpha
Classifier: Intended Audience :: Developers
Classifier: Programming Language :: Python :: 3
Classifier: Programming Language :: Python :: 3.4
Classifier: Topic :: Office/Business :: Financial :: Point-Of-Sale
